singlelayer_hurnet/__init__.py
singlelayer_hurnet/singlelayer_hurnet.py
singlelayer_hurnet-1.0.3.dist-info/LICENSE.txt
singlelayer_hurnet-1.0.3.dist-info/METADATA
singlelayer_hurnet-1.0.3.dist-info/WHEEL
singlelayer_hurnet-1.0.3.dist-info/top_level.txt
singlelayer_hurnet-1.0.3.dist-info/RECORD
